<DialogueTree xmlns:xsi="http://www.w3.org/2001/XMLSchema-instance" xsi:noNamespaceSchemaLocation="https://raw.githubusercontent.com/xen-42/outer-wilds-new-horizons/main/NewHorizons/Schemas/dialogue_schema.xsd">
  <NameField>SIGN</NameField>

  <DialogueNode>
    <Name>INITIAL</Name>
    <EntryCondition>DEFAULT</EntryCondition>
    <Dialogue>
      <Page>
        Mod: Arcanum Adrift
        Authors: The Wrong Warp Team
      </Page>
      <Page>Arcanum Adrift is one of two mods that won first place in the first mod jam held by the Outer Wilds modding community.</Page>
      <Page>This mod adds a unique and stunning location to the game, with the breadcrumb trail to it starting at a Nomai text wall in the observatory museum.</Page>
      <Page>The mod itself makes heavy use of quantum objects, featuring puzzles that require careful alignment of many different objects.</Page>
      <Page>(But seriously, this mod is so good looking, sheesh!)</Page>
    </Dialogue>
  </DialogueNode>
</DialogueTree>
